k_nickname/__init__.py
k_nickname/generator.py
k_nickname-0.1.4.dist-info/METADATA
k_nickname-0.1.4.dist-info/WHEEL
k_nickname-0.1.4.dist-info/RECORD
