Metadata-Version: 2.4
Name: k-nickname
Version: 0.1.4
Summary: Generate random nickname for Korean users.
License: MIT
Author: kyohoonsim
Author-email: kyohoonsim@gmail.com
Requires-Python: >=3.8
Classifier: License :: OSI Approved :: MIT License
Classifier: Programming Language :: Python :: 3
Classifier: Programming Language :: Python :: 3.8
Classifier: Programming Language :: Python :: 3.9
Classifier: Programming Language :: Python :: 3.10
Classifier: Programming Language :: Python :: 3.11
Classifier: Programming Language :: Python :: 3.12
Classifier: Programming Language :: Python :: 3.13
Classifier: Programming Language :: Python :: 3.14
Requires-Dist: emoji (>=2.15.0,<3.0.0)
